bloggo/__init__.py
bloggo/__main__.py
bloggo/core.py
bloggo/hbs.py
bloggo-1.2.2.data/scripts/bloggo
bloggo-1.2.2.dist-info/LICENSE.txt
bloggo-1.2.2.dist-info/METADATA
bloggo-1.2.2.dist-info/WHEEL
bloggo-1.2.2.dist-info/top_level.txt
bloggo-1.2.2.dist-info/RECORD
