Metadata-Version: 2.1
Name: bloggo
Version: 1.2.2
Summary: A blog-oriented static site generator
Home-page: https://github.com/soynomm/bloggo
Author: Nomm
Author-email: nomm@soynomm.com
License: MIT
Platform: UNKNOWN
Classifier: Operating System :: OS Independent
Classifier: Programming Language :: Python :: 3.9
Requires-Dist: pybars3 (>=0.9.7)
Requires-Dist: watchgod (>=0.7)
Requires-Dist: mock (>=4.0.3)
Requires-Dist: Markdown (>=3.3.3)
